deployguard/__init__.py
deployguard/__main__.py
deployguard/cli.py
deployguard/config.py
deployguard/constants.py
deployguard/project.py
deployguard/py.typed
deployguard/scanner.py
deployguard/dynamic/__init__.py
deployguard/dynamic/analyzer.py
deployguard/dynamic/bytecode.py
deployguard/dynamic/rpc_client.py
deployguard/models/__init__.py
deployguard/models/core.py
deployguard/models/dynamic.py
deployguard/models/report.py
deployguard/models/rules.py
deployguard/models/static.py
deployguard/models/testing.py
deployguard/rules/__init__.py
deployguard/rules/base.py
deployguard/rules/executors.py
deployguard/rules/registry.py
deployguard/rules/config/__init__.py
deployguard/rules/config/hardcoded_address.py
deployguard/rules/dynamic/__init__.py
deployguard/rules/dynamic/admin_mismatch.py
deployguard/rules/dynamic/delegatecall_impl.py
deployguard/rules/dynamic/impl_mismatch.py
deployguard/rules/dynamic/non_standard_proxy.py
deployguard/rules/dynamic/uninitialized_proxy.py
deployguard/rules/proxy/__init__.py
deployguard/rules/proxy/hardcoded_impl.py
deployguard/rules/proxy/missing_impl_validation.py
deployguard/rules/proxy/non_atomic_init.py
deployguard/rules/security/__init__.py
deployguard/rules/security/deployer_admin.py
deployguard/rules/security/missing_ownership_transfer.py
deployguard/rules/security/private_key_env.py
deployguard/rules/security/uups_no_authorize.py
deployguard/rules/security/uups_no_disable_init.py
deployguard/rules/security/uups_unsafe_opcode.py
deployguard/rules/security/uups_upgrade_override.py
deployguard/rules/testing/__init__.py
deployguard/rules/testing/no_test.py
deployguard/rules/testing/test_no_run.py
deployguard/static/__init__.py
deployguard/static/analyzer.py
deployguard/static/parsers/__init__.py
deployguard/static/parsers/foundry.py
deployguard/static/parsers/foundry_project.py
deployguard/testing/__init__.py
deployguard/testing/analyzer.py
deployguard/testing/matcher.py
deployguard-0.1.2.dist-info/licenses/LICENSE
deployguard-0.1.2.dist-info/METADATA
deployguard-0.1.2.dist-info/WHEEL
deployguard-0.1.2.dist-info/entry_points.txt
deployguard-0.1.2.dist-info/top_level.txt
deployguard-0.1.2.dist-info/RECORD
