Metadata-Version: 2.4
Name: deployguard
Version: 0.1.2
Summary: CLI tool for auditing Foundry deployment scripts for security vulnerabilities
Author-email: stormblessed <0xstormblessed@proton.me>
License-Expression: Apache-2.0
Project-URL: Homepage, https://github.com/0xstormblessed/deployguard
Project-URL: Repository, https://github.com/0xstormblessed/deployguard
Project-URL: Documentation, https://github.com/0xstormblessed/deployguard#readme
Project-URL: Bug Tracker, https://github.com/0xstormblessed/deployguard/issues
Keywords: security,solidity,foundry,smart-contracts,deployment,audit
Classifier: Development Status :: 3 - Alpha
Classifier: Intended Audience :: Developers
Classifier: Programming Language :: Python :: 3
Classifier: Programming Language :: Python :: 3.10
Classifier: Programming Language :: Python :: 3.11
Classifier: Programming Language :: Python :: 3.12
Classifier: Topic :: Security
Classifier: Topic :: Software Development :: Quality Assurance
Requires-Python: >=3.10
License-File: LICENSE
Requires-Dist: click>=8.0.0
Requires-Dist: rich>=13.0.0
Requires-Dist: aiohttp>=3.8.0
Requires-Dist: pyyaml>=6.0
Requires-Dist: tomli>=2.0.0
Requires-Dist: py-solc-x>=2.0.0
Requires-Dist: packaging>=21.0
Requires-Dist: eth-utils>=2.0.0
Requires-Dist: web3>=6.0.0
Requires-Dist: pathspec>=0.11.0
Provides-Extra: dev
Requires-Dist: pytest>=7.0.0; extra == "dev"
Requires-Dist: pytest-asyncio>=0.21; extra == "dev"
Requires-Dist: pytest-cov>=4.0; extra == "dev"
Requires-Dist: pytest-mock>=3.10; extra == "dev"
Requires-Dist: ruff>=0.1.0; extra == "dev"
Requires-Dist: mypy>=1.0.0; extra == "dev"
Requires-Dist: black>=23.0.0; extra == "dev"
Dynamic: license-file
